LICENSE
many/__init__.py
many/stats/__init__.py
many/stats/categorical_categorical.py
many/stats/config.py
many/stats/continuous_categorical.py
many/stats/continuous_continuous.py
many/stats/continuous_continuous_cmap.py
many/stats/fisher.py
many/stats/utils.py
many/visuals/__init__.py
many/visuals/categorical_categorical.py
many/visuals/continuous_categorical.py
many/visuals/continuous_continuous.py
many/visuals/utils.py
many-0.7.2.dist-info/LICENSE
many-0.7.2.dist-info/METADATA
many-0.7.2.dist-info/WHEEL
many-0.7.2.dist-info/RECORD
