Metadata-Version: 2.1
Name: many
Version: 0.7.2
Summary: Statistical methods for computing many correlations
Home-page: https://github.com/kevinhu/many
License: MIT
Author: Kevin Hu
Author-email: kevinhuwest@gmail.com
Requires-Python: >=3.9,<4.0
Classifier: License :: OSI Approved :: MIT License
Classifier: Programming Language :: Python :: 3
Classifier: Programming Language :: Python :: 3.9
Classifier: Programming Language :: Python :: 3.10
Classifier: Programming Language :: Python :: 3.11
Classifier: Programming Language :: Python :: 3.12
Requires-Dist: adjusttext (>=1.1.1,<2.0.0)
Requires-Dist: matplotlib (>=3.8.4,<4.0.0)
Requires-Dist: numpy (>=1.26.4,<2.0.0)
Requires-Dist: pandas (>=2.2.1,<3.0.0)
Requires-Dist: scikit-learn (>=1.4.1.post1,<2.0.0)
Requires-Dist: scipy (>=1.13.0,<2.0.0)
Requires-Dist: seaborn (>=0.11.0,<0.12.0)
Requires-Dist: statsmodels (>=0.14.1)
Requires-Dist: tqdm (>=4.66.2,<5.0.0)
Project-URL: Repository, https://github.com/kevinhu/many
